<xml version="1.0" encoding="UTF-8"><news><title>Alle Infos zur VMP Mania 2012 online</title><content>Stück für Stück ging es vorwärts, jetzt gibt es alle Informationen zur diesjährigen VMP Mania auf unserer Homepage im Überblick. Teilnehmer, Termine, Regeln, Spiele, alles was unklar ist kann noch einmal nachgeschaut werden. Auch die Ergebnisse der einzelnen Spiele werden sobald verfügbar dort zu finden sein. All das gibt es unter dem Menüpunkt VMP Mania oder ganz bequem über diesen Link:

VMP Mania Info Dashboard</content><author>Behemoth</author><game>VmpClan</game><source></source><year>2012</year><month>02</month><day>20</day><time>17:22</time></news>